{
  "file_id": 228814046471470968207177136399356778002,
  "time_range": [
    1764634727,
    1764634727
  ],
  "dig_records": [
    {
      "addr_heap_hash": [
        0,
        0,
        0,
        0,
        0,
        0,
        0,
        0,
        0,
        0,
        0,
        0,
        0,
        0,
        0,
        0,
        0,
        0,
        0,
        0,
        0,
        0,
        0,
        0,
        0,
        0,
        0,
        0,
        0,
        0,
        0,
        0
      ],
      "p_container": {
        "event_kind": "log_event",
        "severity": "ERROR",
        "tenant_id": "globex"
      },
      "timeclock": {
        "raw_time": 1764634727,
        "mock_time": 8989333902.22123
      },
      "data_container": {
        "data": [
          123,
          34,
          109,
          101,
          115,
          115,
          97,
          103,
          101,
          34,
          58,
          34,
          101,
          114,
          114,
          111,
          114,
          32,
          49,
          48,
          34,
          44,
          34,
          99,
          111,
          100,
          101,
          34,
          58,
          34,
          69,
          95,
          68,
          69,
          77,
          79,
          95,
          69,
          78,
          84,
          69,
          82,
          80,
          82,
          73,
          83,
          69,
          34,
          125
        ],
        "timeclock": {
          "raw_time": 1764634727,
          "mock_time": 8989333902.22123
        },
        "hash_root": [
          0,
          0,
          0,
          0,
          0,
          0,
          0,
          0,
          0,
          0,
          0,
          0,
          0,
          0,
          0,
          0,
          0,
          0,
          0,
          0,
          0,
          0,
          0,
          0,
          0,
          0,
          0,
          0,
          0,
          0,
          0,
          0
        ],
        "params": {
          "event_kind": "log_event",
          "severity": "ERROR",
          "tenant_id": "globex"
        },
        "logic_ref": "service:globex_api",
        "wall": "prod"
      },
      "hook_hash": [
        0,
        0,
        0,
        0,
        0,
        0,
        0,
        0,
        0,
        0,
        0,
        0,
        0,
        0,
        0,
        0,
        0,
        0,
        0,
        0,
        0,
        0,
        0,
        0,
        0,
        0,
        0,
        0,
        0,
        0,
        0,
        0
      ]
    }
  ],
  "merkle_root": [
    143,
    131,
    204,
    5,
    173,
    236,
    205,
    241,
    13,
    174,
    81,
    90,
    252,
    173,
    240,
    17,
    177,
    236,
    141,
    120,
    12,
    218,
    225,
    2,
    59,
    134,
    10,
    122,
    250,
    64,
    49,
    156
  ]
}